black_stripe_detector/__init__.py
black_stripe_detector/detector.py
black_stripe_detector-0.1.2.dist-info/METADATA
black_stripe_detector-0.1.2.dist-info/WHEEL
black_stripe_detector-0.1.2.dist-info/top_level.txt
black_stripe_detector-0.1.2.dist-info/RECORD
